MANIFEST.in
README.rst
setup.cfg
setup.py
ifaddr/__init__.py
ifaddr/_posix.py
ifaddr/_shared.py
ifaddr/_win32.py
ifaddr.egg-info/PKG-INFO
ifaddr.egg-info/SOURCES.txt
ifaddr.egg-info/dependency_links.txt
ifaddr.egg-info/requires.txt
ifaddr.egg-info/top_level.txt