Metadata-Version: 1.0
Name: ifaddr
Version: 0.1.1
Summary: Enumerates all IP addresses on all network adapters of the system.
Home-page: https://github.com/smurn/ifaddr
Author: Stefan C. Mueller
Author-email: stefan.mueller@fhnw.ch
License: UNKNOWN
Platform: UNKNOWN
